pdm_fabric/__init__.py
pdm_fabric/main.py
pdm_fabric-0.1.0.dist-info/entry_points.txt
pdm_fabric-0.1.0.dist-info/WHEEL
pdm_fabric-0.1.0.dist-info/METADATA
pdm_fabric-0.1.0.dist-info/license_files/LICENSE
pdm_fabric-0.1.0.dist-info/RECORD
