Metadata-Version: 2.1
Name: pdm-fabric
Version: 0.1.0
Summary: pdm shortcuts for Fabric projects
License: MIT
Author-email: Abdul Hamid <abdulachik@icloud.com>
Requires-Python: >=3.7
Project-URL: homepage, https://github.com/sicksid/pdm-fabric
